immureii/__init__.py
tests/__init__.py
tests/test_immureii.py
immureii-0.42.10.dist-info/METADATA
immureii-0.42.10.dist-info/WHEEL
immureii-0.42.10.dist-info/top_level.txt
immureii-0.42.10.dist-info/RECORD
